pyrformance/__init__.py
pyrformance/__main__.py
pyrformance/_cli.py
pyrformance/rules/README.md
pyrformance/rules/all-to-and.yaml
pyrformance/rules/any-all-laziness.yaml
pyrformance/rules/any-to-or.yaml
pyrformance/rules/dict-fromkeys.yaml
pyrformance/rules/dict-update.yaml
pyrformance/rules/double-call.yaml
pyrformance/rules/double-startswith.yaml
pyrformance/rules/elif.yaml
pyrformance/rules/filter.yaml
pyrformance/rules/for-compr.yaml
pyrformance/rules/if-len.yaml
pyrformance/rules/join-iters-to-list.yaml
pyrformance/rules/join-iters-to-tuple.yaml
pyrformance/rules/map.yaml
pyrformance/rules/max-to-if.yaml
pyrformance/rules/min-to-if.yaml
pyrformance/rules/re-compile.yaml
pyrformance/rules/set-contains.yaml
pyrformance/rules/str-concat.yaml
pyrformance/rules/str-removeprefix.yaml
pyrformance/rules/str-split-maxsplit.yaml
pyrformance-0.4.0.dist-info/entry_points.txt
pyrformance-0.4.0.dist-info/LICENSE
pyrformance-0.4.0.dist-info/WHEEL
pyrformance-0.4.0.dist-info/METADATA
pyrformance-0.4.0.dist-info/RECORD
