Metadata-Version: 2.1
Name: pyrformance
Version: 0.4.0
Summary: Linter that makes your Python code faster.
Keywords: performance,speed,fast,profiler,linter,semgrep,cli,pythonic
Author-email: Gram <git@orsinium.dev>
Requires-Python: >=3.8
Classifier: Development Status :: 5 - Production/Stable
Classifier: Intended Audience :: Developers
Classifier: License :: OSI Approved :: MIT License
Classifier: Programming Language :: Python
Classifier: Typing :: Typed
Requires-Dist: semgrep
Requires-Dist: isort ; extra == "lint"
Requires-Dist: flake8 ; extra == "lint"
Requires-Dist: unify ; extra == "lint"
Requires-Dist: mypy ; extra == "lint"
Requires-Dist: pytest ; extra == "test"
Requires-Dist: pytest-cov ; extra == "test"
Requires-Dist: pytest-xdist ; extra == "test"
Requires-Dist: true-north ; extra == "test"
Project-URL: Source, https://github.com/orsinium-labs/pyrformance
Provides-Extra: lint
Provides-Extra: test
